onnx/__init__.py
onnx/onnx_pb2.py
onnxds/__init__.py
onnxds/datasets_pb2.py
onnxds/read_dataset.py
onnxds/readtest.py
onnxds/tfgen_dataset.py
onnxds-0.0.2.dist-info/DESCRIPTION.rst
onnxds-0.0.2.dist-info/METADATA
onnxds-0.0.2.dist-info/RECORD
onnxds-0.0.2.dist-info/WHEEL
onnxds-0.0.2.dist-info/metadata.json
onnxds-0.0.2.dist-info/top_level.txt
